bluecon/BlueConAPI.py
bluecon/__init__.py
bluecon/model/AccessDoor.py
bluecon/model/BlueConJSONEncoder.py
bluecon/model/CallLog.py
bluecon/model/DeviceInfo.py
bluecon/model/Pairing.py
bluecon/model/User.py
bluecon/notifications/CallEndNotification.py
bluecon/notifications/CallNotification.py
bluecon/notifications/INotification.py
bluecon/notifications/NotificationBuilder.py
bluecon/oauth/OAuthService.py
bluecon/oauth/OAuthToken.py
bluecon/storage/FileNotificationInfoStorage.py
bluecon/storage/INotificationInfoStorage.py
bluecon/storage/IOAuthTokenStorage.py
bluecon/storage/InMemoryOAuthTokenStorage.py
bluecon-0.4.3.dist-info/METADATA
bluecon-0.4.3.dist-info/WHEEL
bluecon-0.4.3.dist-info/licenses/LICENSE
bluecon-0.4.3.dist-info/RECORD
