Metadata-Version: 2.3
Name: bluecon
Version: 0.4.3
Summary: Library for connecting to Fermax Blue supported doorbells
Project-URL: Homepage, https://bluecon.afonsogarcia.dev
Project-URL: Bug Tracker, https://github.com/AfonsoFGarcia/bluecon/issues
Author-email: Afonso Garcia <bluecon@afonsogarcia.dev>
License-File: LICENSE
Classifier: Development Status :: 4 - Beta
Classifier: Intended Audience :: Developers
Classifier: License :: OSI Approved :: MIT License
Classifier: Operating System :: OS Independent
Classifier: Programming Language :: Python
Classifier: Programming Language :: Python :: 3
Classifier: Programming Language :: Python :: 3.11
Classifier: Topic :: Software Development :: Libraries
Requires-Python: >=3.7
